kquant-0.3.6.dist-info/RECORD
kquant-0.3.6.dist-info/WHEEL
kquant-0.3.6.dist-info/top_level.txt
kquant-0.3.6.dist-info/METADATA
kquant/_config.cpython-39-darwin.so
kquant/__init__.cpython-39-darwin.so
kquant/py.typed
kquant/api.cpython-39-darwin.so
kquant/_utils/__init__.cpython-39-darwin.so
kquant/types/__init__.cpython-39-darwin.so
kquant/analysis/__init__.cpython-39-darwin.so
kquant/analysis/stock/__init__.cpython-39-darwin.so
kquant/analysis/stock/backtest/handle_actions.cpython-39-darwin.so
kquant/analysis/stock/backtest/const.cpython-39-darwin.so
kquant/analysis/stock/backtest/__init__.cpython-39-darwin.so
kquant/analysis/stock/backtest/portfolio.cpython-39-darwin.so
kquant/analysis/stock/backtest/utils.cpython-39-darwin.so
kquant/analysis/stock/backtest/single_stock.cpython-39-darwin.so
kquant/analysis/stock/backtest/log.cpython-39-darwin.so
kquant/analysis/stock/ta/__init__.cpython-39-darwin.so
kquant/analysis/stock/ta/statistics/_variance.cpython-39-darwin.so
kquant/analysis/stock/ta/statistics/_zscore.cpython-39-darwin.so
kquant/analysis/stock/ta/statistics/_kurtosis.cpython-39-darwin.so
kquant/analysis/stock/ta/statistics/_quantile.cpython-39-darwin.so
kquant/analysis/stock/ta/statistics/__init__.cpython-39-darwin.so
kquant/analysis/stock/ta/statistics/_median.cpython-39-darwin.so
kquant/analysis/stock/ta/statistics/_stdev.cpython-39-darwin.so
kquant/analysis/stock/ta/statistics/_mad.cpython-39-darwin.so
kquant/analysis/stock/ta/statistics/_skew.cpython-39-darwin.so
kquant/analysis/stock/ta/statistics/_entropy.cpython-39-darwin.so
kquant/analysis/stock/ta/momentum/_cfo.cpython-39-darwin.so
kquant/analysis/stock/ta/momentum/_mom.cpython-39-darwin.so
kquant/analysis/stock/ta/momentum/_psl.cpython-39-darwin.so
kquant/analysis/stock/ta/momentum/_coppock.cpython-39-darwin.so
kquant/analysis/stock/ta/momentum/_kst.cpython-39-darwin.so
kquant/analysis/stock/ta/momentum/_er.cpython-39-darwin.so
kquant/analysis/stock/ta/momentum/_cg.cpython-39-darwin.so
kquant/analysis/stock/ta/momentum/_tsi.cpython-39-darwin.so
