Metadata-Version: 2.1
Name: kquant
Version: 0.3.6
Summary: KOSCOM Quant
Author: KOSCOM
Author-email: joelkim@koscom.co.kr
License: Commercial
Keywords: quant
Classifier: Development Status :: 4 - Beta
Classifier: Programming Language :: Python
Classifier: Programming Language :: Python :: 3.9
Classifier: Programming Language :: Python :: 3.10
Classifier: Programming Language :: Python :: 3.11
Classifier: Programming Language :: Python :: 3.12
Classifier: Programming Language :: Python :: Implementation :: CPython
Requires-Python: >=3.9
Requires-Dist: boto3
Requires-Dist: ipython
Requires-Dist: numpy
Requires-Dist: pandas
Requires-Dist: pandas-ta
Requires-Dist: plotly
Requires-Dist: python-dateutil
Requires-Dist: requests
